colissimo.py
setup.cfg
setup.py
colissimo.egg-info/PKG-INFO
colissimo.egg-info/SOURCES.txt
colissimo.egg-info/dependency_links.txt
colissimo.egg-info/entry_points.txt
colissimo.egg-info/requires.txt
colissimo.egg-info/top_level.txt