Metadata-Version: 1.1
Name: colissimo
Version: 0.3
Summary: Follow you Colissimo parcels from your shell
Home-page: https://github.com/stac47/colissimo
Author: Laurent Stacul
Author-email: laurent.stacul@gmail.com
License: UNKNOWN
Download-URL: https://github.com/stac47/colissimo/archive/0.3.tar.gz
Keywords: parcel,tool,La Poste
Platform: UNKNOWN
